github_issue_bot/__init__.py
github_issue_bot/__main__.py
github_issue_bot-0.1.0.dist-info/entry_points.txt
github_issue_bot-0.1.0.dist-info/LICENSE
github_issue_bot-0.1.0.dist-info/WHEEL
github_issue_bot-0.1.0.dist-info/METADATA
github_issue_bot-0.1.0.dist-info/RECORD
